{

  "response": [{

      "id": 1,

      "latitude": 37.2330278,

      "longitude": -121.87908333333333,

      "objectName": "Coast live oak tree orchard",

      "objectImage": "https://www.bayareaolderadults.org/images/mobileapp/guadalupeOakGrovePark1.jpg",

      "objectType": "Tree",

      "videoLink": "https://youtu.be/nMoJZ-utf8c"

    },

    {

      "id": 2,

      "latitude": 37.2331944,

      "longitude": -121.87919444444444,

      "objectName": "Acorn woodpecker in interior oak",
      "objectImage": "https://www.bayareaolderadults.org/images/mobileapp/guadalupeOakGrovePark2.jpg",

      "objectType": "Bird",

      "videoLink": "https://youtu.be/QOVZKQgX2sc"

    },

    {

      "id": 3,

      "latitude": 37.2337222,

      "longitude": -121.87944444444443,

      "objectName": "Blue oak tree",

      "objectImage": "https://www.bayareaolderadults.org/images/mobileapp/guadalupeOakGrovePark2.jpg",

      "objectType": "Tree",

      "videoLink": "https://youtu.be/NFCk3rfbSac"

    },

    {

      "id": 4,

      "latitude": 37.2343611,

      "longitude": -121.88047222222221,

      "objectName": "Pecked Oak Tree",

      "objectImage": "https://www.bayareaolderadults.org/images/mobileapp/guadalupeOakGrovePark4.jpg",

      "objectType": "Tree",

      "videoLink": "https://youtu.be/uiXpfmJ59_4"

    },

    {

      "id": 5,

      "latitude": 37.2356944,

      "longitude": -121.88072222222222,

      "objectName": "Oak Grove Overlook",

      "objectImage": "https://www.bayareaolderadults.org/images/mobileapp/guadalupeOakGrovePark5.jpg",

      "objectType": "Overlook",

      "videoLink": "https://youtu.be/ilYhDBGKKdg"

    },

    {

      "id": 6,

      "latitude": 37.2357778,

      "longitude": -121.88077777777777,

      "objectName": "Western Fence Lizard",

      "objectImage": "https://www.bayareaolderadults.org/images/mobileapp/guadalupeOakGrovePar6.jpg",

      "objectType": "Lizard",

      "videoLink": "https://youtu.be/Aqe7LvyfHyA"

    },

    {

      "id": 7,

      "latitude": 37.2358889,

      "longitude": -121.88074999999999,

      "objectName": "California Sagebrush",

      "objectImage": "https://www.bayareaolderadults.org/images/mobileapp/guadalupeOakGrovePark7.jpg",

      "objectType": "Dwarf",

      "videoLink": "https://youtu.be/1n5fcDsKoKg"

    }]

}
